beanbag_docutils/__init__.py
beanbag_docutils/sphinx/__init__.py
beanbag_docutils/sphinx/ext/__init__.py
beanbag_docutils/sphinx/ext/autodoc_utils.py
beanbag_docutils/sphinx/ext/collect_files.py
beanbag_docutils/sphinx/ext/django_utils.py
beanbag_docutils/sphinx/ext/extlinks.py
beanbag_docutils/sphinx/ext/github.py
beanbag_docutils/sphinx/ext/http_role.py
beanbag_docutils/sphinx/ext/image_srcsets.py
beanbag_docutils/sphinx/ext/intersphinx_utils.py
beanbag_docutils/sphinx/ext/json_writer.py
beanbag_docutils/sphinx/ext/metadata.py
beanbag_docutils/sphinx/ext/ref_utils.py
beanbag_docutils/sphinx/ext/retina_images.py
beanbag_docutils/sphinx/ext/tests/__init__.py
beanbag_docutils/sphinx/ext/tests/test_autodoc_utils.py
beanbag_docutils/sphinx/ext/tests/test_django_utils.py
beanbag_docutils/sphinx/ext/tests/test_extlinks.py
beanbag_docutils/sphinx/ext/tests/test_github.py
beanbag_docutils/sphinx/ext/tests/test_http_role.py
beanbag_docutils/sphinx/ext/tests/test_image_srcsets.py
beanbag_docutils/sphinx/ext/tests/test_json_writer.py
beanbag_docutils/sphinx/ext/tests/test_metadata.py
beanbag_docutils/sphinx/ext/tests/test_ref_utils.py
beanbag_docutils/sphinx/ext/tests/testcase.py
beanbag_docutils/sphinx/ext/tests/testdata/__init__.py
beanbag_docutils/sphinx/ext/tests/testdata/github_linkcode_module.py
beanbag_docutils-2.4.dist-info/AUTHORS
beanbag_docutils-2.4.dist-info/COPYING
beanbag_docutils-2.4.dist-info/METADATA
beanbag_docutils-2.4.dist-info/WHEEL
beanbag_docutils-2.4.dist-info/top_level.txt
beanbag_docutils-2.4.dist-info/RECORD
